fairness/__init__.py
fairness/config_parser.py
fairness/fairness_users.py
fairness/metrics.py
fairness/node.py
fairness/openstack_driver.py
fairness/virtual_machines.py
fairness/virtual_machines_tester.py
fairness/controller/__init__.py
fairness/node_service/__init__.py
fairness/node_service/controller_manager.py
fairness/node_service/crs.py
fairness/node_service/libvirt_driver.py
fairness/node_service/node_manager.py
fairness/node_service/nri.py
fairness/node_service/rui.py
fairness/node_service/utils_controller.py
fairness_service-0.1.1.dev1.dist-info/DESCRIPTION.rst
fairness_service-0.1.1.dev1.dist-info/METADATA
fairness_service-0.1.1.dev1.dist-info/RECORD
fairness_service-0.1.1.dev1.dist-info/WHEEL
fairness_service-0.1.1.dev1.dist-info/entry_points.txt
fairness_service-0.1.1.dev1.dist-info/metadata.json
fairness_service-0.1.1.dev1.dist-info/top_level.txt
